{
  "speeches": [
    {
      "subjectKeyword": "speech1",
      "speechContent": "speech 1 content 1",
      "author": "admin-user",
      "date": "2018-11-22",
      "id": "4ddae619-870a-e878-26a5-edc69bc3d448",
      "userId": "testUser123"
    },
    {
      "subjectKeyword": "speech2",
      "speechContent": "speech2 content 2\ntest 123",
      "author": "admin-user",
      "date": "2018-11-23",
      "id": "6dc334d2-09a0-4bc0-6c4d-04aae1d61797",
      "userId": "testUser123"
    },
    {
      "subjectKeyword": "speech5",
      "speechContent": "speech 5 content 5",
      "author": "unknown-user",
      "date": "2018-11-22",
      "id": "4ddae619-870a-e878-26a5-edc69bc3d448",
      "userId": "testUser124"
    },
    {
      "subjectKeyword": "speech8",
      "speechContent": "speech8 content 2\ntest 128",
      "author": "unknown-user",
      "date": "2018-11-23",
      "id": "6dc334d2-09a0-4bc0-6c4d-04aae1d61797",
      "userId": "testUser125"
    },
    {
      "subjectKeyword": "speech4",
      "speechContent": "speech 4 content 4",
      "author": "unknown-user",
      "date": "2018-11-22",
      "id": "4ddae619-870a-e878-26a5-edc69bc3d448",
      "userId": "testUser126"
    },
    {
      "subjectKeyword": "speech7",
      "speechContent": "speech7 content 2\ntest 123",
      "author": "unknown-user",
      "date": "2018-11-23",
      "id": "6dc334d2-09a0-4bc0-6c4d-04aae1d61797",
      "userId": "testUser127"
    },
    {
      "subjectKeyword": "test speech",
      "speechContent": "dsfdwf\newr\new\nr\new\nr\new\nrew\nr",
      "author": "admin-user",
      "date": "2018-11-14",
      "id": "bbbcd244-0345-f9a3-8574-6bdac8c8edaa",
      "userId": "testUser123"
    },
    {
      "subjectKeyword": "test speech",
      "speechContent": "test speech from abc",
      "author": "user 123",
      "date": "2018-11-23",
      "id": "837b9598-9987-380d-790e-c396c050e6f5",
      "userId": "testUser123"
    },
    {
      "subjectKeyword": "test",
      "speechContent": "test speech 22-11 dsfdsaf\n\nfdsa\nf\ndsa\nf\ndsa\nf\ndsa\nf\ndsaf\ndsaf\ndsa\nfdsa\nfdsa\nf\ndsa\nf\ndsa\nf\ndsafffff  sfdsafdsa  safddsafdsa   sfswfdsa  swfddfsaf",
      "author": "Admin",
      "date": "2018-11-24",
      "id": "a063baf9-a946-508a-bdfc-596ee5d55cf1",
      "userId": "testUser123"
    }
  ]
}